django_mongoengine_forms-0.4.6.dist-info/METADATA
django_mongoengine_forms-0.4.6.dist-info/RECORD
django_mongoengine_forms-0.4.6.dist-info/WHEEL
django_mongoengine_forms-0.4.6.dist-info/top_level.txt
mongodbforms/__init__.py
mongodbforms/documentoptions.py
mongodbforms/documents.py
mongodbforms/fieldgenerator.py
mongodbforms/fields.py
mongodbforms/util.py
mongodbforms/widgets.py
tests/__init__.py
tests/test_document.py
tests/test_lazywrapper.py
tests/test_recursive_reference.py
tests/fixtures/__init__.py
tests/fixtures/recursive_definition.py
