Metadata-Version: 1.1
Name: django-mongoengine-forms
Version: 0.4.6
Summary: An implementation of django forms using mongoengine.
Home-page: https://github.com/thomwiggers/django-mongoengine-forms/
Author: Thom Wiggers
Author-email: thom@thomwiggers.nl
License: New BSD License
Platform: UNKNOWN
Classifier: Development Status :: 3 - Alpha
Classifier: Environment :: Web Environment
Classifier: Intended Audience :: Developers
Classifier: License :: OSI Approved :: BSD License
Classifier: Operating System :: OS Independent
Classifier: Programming Language :: Python
Classifier: Framework :: Django
Provides: mongodbforms
Obsoletes: mongodbforms
